{
    "20": {
        "fg_pct": 0.465,
        "ft_pct": 0.782,
        "fg3_pct": 0.368,
        "reb": 45.2,
        "ast": 24.1,
        "pts": 112.5
    },
    "22": {
        "fg_pct": 0.472,
        "ft_pct": 0.765,
        "fg3_pct": 0.355,
        "reb": 43.8,
        "ast": 25.4,
        "pts": 110.8
    },
    "28": {
        "fg_pct": 0.481,
        "ft_pct": 0.79,
        "fg3_pct": 0.375,
        "reb": 44.0,
        "ast": 28.5,
        "pts": 118.2
    },
    "2": {
        "fg_pct": 0.495,
        "ft_pct": 0.812,
        "fg3_pct": 0.395,
        "reb": 46.5,
        "ast": 29.1,
        "pts": 122.5
    },
    "4": {
        "fg_pct": 0.455,
        "ft_pct": 0.75,
        "fg3_pct": 0.34,
        "reb": 41.5,
        "ast": 23.0,
        "pts": 108.0
    },
    "8": {
        "fg_pct": 0.49,
        "ft_pct": 0.77,
        "fg3_pct": 0.36,
        "reb": 47.0,
        "ast": 28.0,
        "pts": 115.0
    },
    "1": {
        "fg_pct": 0.457,
        "ft_pct": 0.784,
        "fg3_pct": 0.317,
        "reb": 39.3,
        "ast": 22.0,
        "pts": 100.7
    },
    "3": {
        "fg_pct": 0.43,
        "ft_pct": 0.826,
        "fg3_pct": 0.376,
        "reb": 42.3,
        "ast": 22.0,
        "pts": 110.7
    },
    "5": {
        "fg_pct": 0.439,
        "ft_pct": 0.765,
        "fg3_pct": 0.341,
        "reb": 49.3,
        "ast": 26.3,
        "pts": 111.0
    },
    "6": {
        "fg_pct": 0.545,
        "ft_pct": 0.711,
        "fg3_pct": 0.437,
        "reb": 41.0,
        "ast": 28.0,
        "pts": 128.0
    },
    "7": {
        "fg_pct": 0.421,
        "ft_pct": 0.776,
        "fg3_pct": 0.347,
        "reb": 48.3,
        "ast": 25.3,
        "pts": 110.7
    },
    "9": {
        "fg_pct": 0.463,
        "ft_pct": 0.806,
        "fg3_pct": 0.346,
        "reb": 41.3,
        "ast": 24.7,
        "pts": 109.3
    },
    "10": {
        "fg_pct": 0.477,
        "ft_pct": 0.724,
        "fg3_pct": 0.383,
        "reb": 54.7,
        "ast": 30.7,
        "pts": 123.3
    },
    "11": {
        "fg_pct": 0.404,
        "ft_pct": 0.74,
        "fg3_pct": 0.339,
        "reb": 45.7,
        "ast": 17.0,
        "pts": 105.0
    },
    "12": {
        "fg_pct": 0.488,
        "ft_pct": 0.734,
        "fg3_pct": 0.269,
        "reb": 36.3,
        "ast": 29.3,
        "pts": 109.0
    },
    "13": {
        "fg_pct": 0.469,
        "ft_pct": 0.732,
        "fg3_pct": 0.328,
        "reb": 36.0,
        "ast": 21.7,
        "pts": 82.0
    },
    "14": {
        "fg_pct": 0.496,
        "ft_pct": 0.807,
        "fg3_pct": 0.363,
        "reb": 42.7,
        "ast": 29.0,
        "pts": 121.3
    },
    "15": {
        "fg_pct": 0.474,
        "ft_pct": 0.696,
        "fg3_pct": 0.374,
        "reb": 42.0,
        "ast": 30.0,
        "pts": 119.3
    },
    "16": {
        "fg_pct": 0.43,
        "ft_pct": 0.74,
        "fg3_pct": 0.348,
        "reb": 42.7,
        "ast": 27.0,
        "pts": 105.7
    },
    "17": {
        "fg_pct": 0.496,
        "ft_pct": 0.744,
        "fg3_pct": 0.362,
        "reb": 41.0,
        "ast": 22.7,
        "pts": 110.0
    },
    "18": {
        "fg_pct": 0.453,
        "ft_pct": 0.786,
        "fg3_pct": 0.367,
        "reb": 43.3,
        "ast": 23.3,
        "pts": 110.7
    },
    "19": {
        "fg_pct": 0.439,
        "ft_pct": 0.776,
        "fg3_pct": 0.347,
        "reb": 41.7,
        "ast": 26.0,
        "pts": 110.3
    },
    "21": {
        "fg_pct": 0.444,
        "ft_pct": 0.75,
        "fg3_pct": 0.276,
        "reb": 49.3,
        "ast": 23.3,
        "pts": 114.7
    },
    "23": {
        "fg_pct": 0.412,
        "ft_pct": 0.739,
        "fg3_pct": 0.275,
        "reb": 43.7,
        "ast": 17.3,
        "pts": 111.3
    },
    "24": {
        "fg_pct": 0.483,
        "ft_pct": 0.773,
        "fg3_pct": 0.404,
        "reb": 41.0,
        "ast": 28.7,
        "pts": 115.3
    },
    "25": {
        "fg_pct": 0.422,
        "ft_pct": 0.793,
        "fg3_pct": 0.33,
        "reb": 46.7,
        "ast": 24.0,
        "pts": 110.7
    },
    "26": {
        "fg_pct": 0.478,
        "ft_pct": 0.859,
        "fg3_pct": 0.37,
        "reb": 36.7,
        "ast": 26.0,
        "pts": 117.7
    },
    "27": {
        "fg_pct": 0.456,
        "ft_pct": 0.808,
        "fg3_pct": 0.337,
        "reb": 50.3,
        "ast": 25.0,
        "pts": 106.3
    },
    "29": {
        "fg_pct": 0.386,
        "ft_pct": 0.77,
        "fg3_pct": 0.29,
        "reb": 46.7,
        "ast": 21.0,
        "pts": 103.3
    },
    "30": {
        "fg_pct": 0.416,
        "ft_pct": 0.797,
        "fg3_pct": 0.339,
        "reb": 38.3,
        "ast": 23.0,
        "pts": 105.3
    }
}